src/__init__.py
src/app.py
src/cfg/__init__.py
jbac-0.0.1.dist-info/METADATA
jbac-0.0.1.dist-info/WHEEL
jbac-0.0.1.dist-info/entry_points.txt
jbac-0.0.1.dist-info/top_level.txt
jbac-0.0.1.dist-info/RECORD
