Metadata-Version: 2.1
Name: jbac
Version: 0.0.1
Requires-Dist: argsy (>=1.0.3)
Requires-Dist: requests
Requires-Dist: python-dotenv
